e3dc/__init__.py
e3dc/_rscp_dto.py
e3dc/_rscp_encrypt_decrypt.py
e3dc/_rscp_exceptions.py
e3dc/_rscp_utils.py
e3dc/e3dc.py
e3dc/rscp_tag.py
e3dc/rscp_type.py
e3dc/test/__init__.py
e3dc/test/test_RSCPEncryptDecrypt.py
e3dc/test/test_RSCPTag.py
e3dc/test/test_RSCPType.py
e3dc/test/test_RSCPUtils.py
e3dc-0.0.4.dist-info/LICENSE
e3dc-0.0.4.dist-info/METADATA
e3dc-0.0.4.dist-info/WHEEL
e3dc-0.0.4.dist-info/top_level.txt
e3dc-0.0.4.dist-info/RECORD
