Metadata-Version: 2.1
Name: e3dc
Version: 0.0.4
Summary: UNKNOWN
Home-page: https://www.github.com/python-e3dc
Author: J. Brunswicker
Author-email: johannes.brunswicker@gmail.com
License: MIT
Platform: UNKNOWN
Classifier: Development Status :: 2 - Pre-Alpha
Classifier: License :: OSI Approved :: MIT License
Classifier: Programming Language :: Python :: 3.7
Classifier: Topic :: Communications
Classifier: Topic :: Software Development :: Libraries
Requires-Dist: py3rijndael
Requires-Dist: pytest
